<annotation>
	<folder></folder>
	<filename>000498_jpg.rf.fe78d0119e60c96f822899c34b804871.jpg</filename>
	<path>000498_jpg.rf.fe78d0119e60c96f822899c34b804871.jpg</path>
	<source>
		<database>roboflow.com</database>
	</source>
	<size>
		<width>1000</width>
		<height>704</height>
		<depth>3</depth>
	</size>
	<segmented>0</segmented>
	<object>
		<name>helmet</name>
		<pose>Unspecified</pose>
		<truncated>0</truncated>
		<difficult>0</difficult>
		<occluded>0</occluded>
		<bndbox>
			<xmin>146</xmin>
			<xmax>297</xmax>
			<ymin>51</ymin>
			<ymax>154</ymax>
		</bndbox>
	</object>
	<object>
		<name>helmet</name>
		<pose>Unspecified</pose>
		<truncated>0</truncated>
		<difficult>0</difficult>
		<occluded>0</occluded>
		<bndbox>
			<xmin>344</xmin>
			<xmax>457</xmax>
			<ymin>94</ymin>
			<ymax>177</ymax>
		</bndbox>
	</object>
	<object>
		<name>helmet</name>
		<pose>Unspecified</pose>
		<truncated>0</truncated>
		<difficult>0</difficult>
		<occluded>0</occluded>
		<bndbox>
			<xmin>478</xmin>
			<xmax>544</xmax>
			<ymin>153</ymin>
			<ymax>193</ymax>
		</bndbox>
	</object>
	<object>
		<name>helmet</name>
		<pose>Unspecified</pose>
		<truncated>0</truncated>
		<difficult>0</difficult>
		<occluded>0</occluded>
		<bndbox>
			<xmin>618</xmin>
			<xmax>680</xmax>
			<ymin>147</ymin>
			<ymax>187</ymax>
		</bndbox>
	</object>
	<object>
		<name>helmet</name>
		<pose>Unspecified</pose>
		<truncated>0</truncated>
		<difficult>0</difficult>
		<occluded>0</occluded>
		<bndbox>
			<xmin>721</xmin>
			<xmax>819</xmax>
			<ymin>127</ymin>
			<ymax>193</ymax>
		</bndbox>
	</object>
</annotation>
