<annotation>
	<folder></folder>
	<filename>001464_jpg.rf.6bb61a2a78a27253efdef9c92b36fa57.jpg</filename>
	<path>001464_jpg.rf.6bb61a2a78a27253efdef9c92b36fa57.jpg</path>
	<source>
		<database>roboflow.com</database>
	</source>
	<size>
		<width>800</width>
		<height>533</height>
		<depth>3</depth>
	</size>
	<segmented>0</segmented>
	<object>
		<name>helmet</name>
		<pose>Unspecified</pose>
		<truncated>0</truncated>
		<difficult>0</difficult>
		<occluded>0</occluded>
		<bndbox>
			<xmin>238</xmin>
			<xmax>564</xmax>
			<ymin>46</ymin>
			<ymax>252</ymax>
		</bndbox>
	</object>
</annotation>
