<annotation>
	<folder></folder>
	<filename>part2_000242_jpg.rf.bca94709e79ea7ba10995ceffd77d43a.jpg</filename>
	<path>part2_000242_jpg.rf.bca94709e79ea7ba10995ceffd77d43a.jpg</path>
	<source>
		<database>roboflow.com</database>
	</source>
	<size>
		<width>500</width>
		<height>500</height>
		<depth>3</depth>
	</size>
	<segmented>0</segmented>
	<object>
		<name>helmet</name>
		<pose>Unspecified</pose>
		<truncated>0</truncated>
		<difficult>0</difficult>
		<occluded>0</occluded>
		<bndbox>
			<xmin>139</xmin>
			<xmax>401</xmax>
			<ymin>15</ymin>
			<ymax>175</ymax>
		</bndbox>
	</object>
</annotation>
